ntfybro/__init__.py
ntfybro/notifier.py
ntfybro-1.0.0.dist-info/licenses/LICENSE.txt
ntfybro-1.0.0.dist-info/METADATA
ntfybro-1.0.0.dist-info/WHEEL
ntfybro-1.0.0.dist-info/top_level.txt
ntfybro-1.0.0.dist-info/RECORD
